CHANGES
LICENSE
MANIFEST.in
README.md
setup.cfg
setup.py
django_solo_grappelli.egg-info/PKG-INFO
django_solo_grappelli.egg-info/SOURCES.txt
django_solo_grappelli.egg-info/dependency_links.txt
django_solo_grappelli.egg-info/top_level.txt
solo/__init__.py
solo/admin.py
solo/apps.py
solo/models.py
solo/settings.py
solo/templates/admin/solo/change_form.html
solo/templates/admin/solo/object_history.html
solo/templatetags/__init__.py
solo/templatetags/solo_tags.py
solo/tests/__init__.py
solo/tests/models.py
solo/tests/settings.py
solo/tests/tests.py