Metadata-Version: 1.1
Name: django-solo-grappelli
Version: 1.1.2
Summary: django-solo helps working with singletons: things like global settings that you want to edit from the admin site.
